[
  [
    "CWTQ2YA648J5ZGQ9",
    {
      "customer": "Dussmann",
      "name": "Bando Gara Ivrea",
      "date": "08:23 03/04/2023"
    }
  ],
  [
    "UOQR3JJKXCGB1EMC",
    {
      "customer": "AXA",
      "name": "Instant Cover Check",
      "date": "08:23 03/04/2023"
    }
  ],
  [
    "8FNNX6DHCUHS27CC",
    {
      "customer": "xTech FS",
      "name": "Annual Reports",
      "date": "08:23 03/04/2023"
    }
  ],
  [
    "96M23TCJG4A7VUUF",
    {
      "customer": "IBM",
      "name": "Technical Documents",
      "date": "08:23 03/04/2023"
    }
  ],
  [
    "MJ6AP276WPV8BEZN",
    {
      "customer": "Pizzarotti",
      "name": "Knowledge Management",
      "date": "00:05 25/05/2023"
    }
  ],
  [
    "Z74183US7TGKDWLE",
    {
      "customer": "Google",
      "name": "Smarthink",
      "date": "00:05 25/05/2023"
    }
  ]
]